minecraftstats/__init__.py
minecraftstats/bedwarsstats.py
minecraftstats/duelstats.py
minecraftstats/errors.py
minecraftstats/generalstats.py
minecraftstats/minecraftstats.py
minecraftstats/skywarsstats.py
minecraftstats/utils.py
minecraftstats-1.1.6.dist-info/LICENSE
minecraftstats-1.1.6.dist-info/METADATA
minecraftstats-1.1.6.dist-info/WHEEL
minecraftstats-1.1.6.dist-info/top_level.txt
minecraftstats-1.1.6.dist-info/RECORD
