Metadata-Version: 2.1
Name: minecraftstats
Version: 1.1.6
Summary: A python library allowing the user to get stats from Hypixel in Minecraft.
Home-page: https://github.com/JustBennnn/minecraftstats
Author: JustBen
Author-email: justben009@gmail.com
License: MIT
Project-URL: Issue Tracker, https://github.com/JustBennnn/minecraftstats/issues
Keywords: minecraft,api-wrapper,mojang,mojang-api
Platform: UNKNOWN
Classifier: Programming Language :: Python :: 3
Classifier: Development Status :: 5 - Production/Stable
Classifier: Intended Audience :: Developers
Classifier: License :: OSI Approved :: MIT License
Classifier: Operating System :: OS Independent
Classifier: Natural Language :: English
Classifier: Topic :: Internet :: WWW/HTTP
Classifier: Topic :: Software Development :: Libraries
Classifier: Topic :: Software Development :: Libraries :: Python Modules
Classifier: Topic :: Utilities
Requires-Python: >=3.7
License-File: LICENSE
Requires-Dist: requests
Requires-Dist: pydantic
Requires-Dist: mojang
